{"tabs":[{"id":"9afc0e72-3816-4b4d-b87b-5098084c663f","pane":"main","current":true,"path":"F:\\Adx\\Adp\\adp-Matter\\resources\\static\\askia.ajax.js","type":"file"},{"id":"8b4d7d14-d771-4fe5-8ea6-3ac1b9060f7b","pane":"main","path":"F:\\Adx\\Adp\\adp-Matter\\config.xml","type":"projectSettings","mode":"form"},{"id":"317addb6-8594-4410-bfb7-fee1d9b5b535","pane":"main","path":"F:\\Adx\\Adp\\Matter\\resources\\dynamic\\styles.css","type":"file"},{"id":"c4be8639-f9c9-4d4e-adc2-a3ffb0da5e76","pane":"main","path":"F:\\Adx\\Adp\\Matter\\config.xml","type":"projectSettings","mode":"code","adxVersion":"2.1.0","adxType":"adp"},{"id":"99f15a0a-3d76-4d72-9634-1e0d7b457c91","pane":"main","path":"F:\\Adx\\Adp\\Matter\\resources\\dynamic\\default.html","type":"file"},{"id":"8532f4a1-872b-49f7-9546-0f94bff5f1e7","pane":"main","path":"F:\\Adx\\Adp\\Matter\\resources\\static\\styles.css","type":"file"},{"id":"2a27aae3-d653-469f-97fe-a4d1e7f2c702","pane":"main","path":"F:\\Adx\\Adp\\Matter\\resources\\static\\styles.min.css","type":"file"}]}